simple_cqrs/__init__.py
simple_cqrs/cqrs/__init__.py
simple_cqrs/cqrs/command_bus.py
simple_cqrs/cqrs/domain.py
simple_cqrs/cqrs/eventsourcing.py
simple_cqrs/cqrs/handlers.py
simple_cqrs/cqrs/interfaces.py
simple_cqrs/debugger.py
simple_cqrs/domain_event.py
simple_cqrs/domain_event_bus.py
simple_cqrs/domain_event_bus_tests.py
simple_cqrs/domain_subscriber.py
simple_cqrs/helpers/__init__.py
simple_cqrs/helpers/typing.py
simple_cqrs-1.0.0.dist-info/LICENSE
simple_cqrs-1.0.0.dist-info/WHEEL
simple_cqrs-1.0.0.dist-info/METADATA
simple_cqrs-1.0.0.dist-info/RECORD
